requirements.txt
setup.py
bin/fource
lib/fource/__init__.py
lib/fource/config.py
lib/fource/controller.py
lib/fource/settings.py
lib/fource.egg-info/PKG-INFO
lib/fource.egg-info/SOURCES.txt
lib/fource.egg-info/dependency_links.txt
lib/fource.egg-info/requires.txt
lib/fource.egg-info/top_level.txt
lib/fource/feedengine/__init__.py
lib/fource/feedengine/stashboard.py
lib/fource/parser/__init__.py
lib/fource/parser/f_yaml.py
lib/fource/protocol/__init__.py
lib/fource/protocol/http.py
lib/fource/storage/__init__.py
lib/fource/storage/mongo.py
lib/fource/template_engine/__init__.py
lib/fource/template_engine/f_jinja2.py
lib/fource/utils/__init__.py
lib/fource/utils/util.py