Metadata-Version: 1.1
Name: fource
Version: 0.14
Summary: Fully automated status board application
Home-page: http://fource.in/
Author: Team Fource
Author-email: hi@fource.in
License: MIT
Platform: UNKNOWN
Classifier: Programming Language :: Python
Classifier: Operating System :: OS Independent
Classifier: License :: OSI Approved :: MIT License
Classifier: Intended Audience :: Developers
Classifier: Development Status :: 4 - Beta
Classifier: Environment :: Console
Classifier: Topic :: Utilities
Classifier: License :: OSI Approved :: MIT License
